pbg/__init__.py
pbg/breeding/__init__.py
pbg/genomics/__init__.py
pbg-0.1.0.dist-info/METADATA
pbg-0.1.0.dist-info/WHEEL
pbg-0.1.0.dist-info/top_level.txt
pbg-0.1.0.dist-info/RECORD
