Metadata-Version: 2.4
Name: pbg
Version: 0.1.0
Summary: (Coming soon...) Powerful python package for analyzing and visualizing plant breeding and genomics data.
Author-email: "Narinder Singh, PhD" <n@singh.phd>
Requires-Python: >=3.13
Requires-Dist: matplotlib>=3.10.6
Requires-Dist: numpy>=2.3.3
Requires-Dist: pandas>=2.3.2
